{
  "columns":
  ["", "Pipelined", "II", "Bottleneck", "Details"]
  , "children":
  [
    {
      "name":"Kernel: oskar_process_all_tiles"
      , "data":
      ["", "", ""]
      , "debug":
      [
        [
          {
            "filename":"/home/ania/git_tile_v2/gridding_kernels_tile.cl"
            , "line":54
          }
        ]
      ]
      , "details":
      [
        {
          "type":"brief"
          , "text":"Single work-item execution"
        }
        , {
          "type":"text"
          , "text":"Single work-item execution"
        }
        , {
          "type":"text"
          , "text":"See %L for more information"
          , "links":
          [
            {
              "guide":"Best Practices Guide : Kernels"
              , "link":"https://www.altera.com/documentation/mwh1391807516407.html#ipp1476408832230"
            }
          ]
        }
      ]
      , "children":
      [
        {
          "name":"oskar_process_all_tiles.B1"
          , "data":
          ["Yes", ">=1", "n/a"]
          , "debug":
          [
            [
              {
                "filename":"/home/ania/git_tile_v2/gridding_kernels_tile.cl"
                , "line":82
              }
            ]
            , [
              {
                "filename":"/home/ania/git_tile_v2/gridding_kernels_tile.cl"
                , "line":82
              }
            ]
          ]
          , "details":
          [
            {
              "type":"brief"
              , "text":" "
            }
            , {
              "type":"text"
              , "text":"II is an approximation due to variable inner loop trip count."
              , "links":
              [
                {
                  "view":"Verification statistics"
                }
              ]
            }
          ]
          , "children":
          [
            {
              "name":"oskar_process_all_tiles.B2"
              , "data":
              ["Yes", "~1", "n/a"]
              , "debug":
              [
                [
                  {
                    "filename":"/home/ania/git_tile_v2/gridding_kernels_tile.cl"
                    , "line":105
                  }
                ]
                , [
                  {
                    "filename":"/home/ania/git_tile_v2/gridding_kernels_tile.cl"
                    , "line":105
                  }
                ]
                , [
                  {
                    "filename":"/home/ania/git_tile_v2/gridding_kernels_tile.cl"
                    , "line":146
                  }
                ]
                , [
                  {
                    "filename":"/home/ania/git_tile_v2/gridding_kernels_tile.cl"
                    , "line":147
                  }
                ]
                , [
                  {
                    "filename":"/home/ania/git_tile_v2/gridding_kernels_tile.cl"
                    , "line":149
                  }
                ]
                , [
                  {
                    "filename":"/home/ania/git_tile_v2/gridding_kernels_tile.cl"
                    , "line":150
                  }
                ]
                , [
                  {
                    "filename":"/home/ania/git_tile_v2/gridding_kernels_tile.cl"
                    , "line":153
                  }
                ]
                , [
                  {
                    "filename":"/home/ania/git_tile_v2/gridding_kernels_tile.cl"
                    , "line":153
                  }
                ]
                , [
                  {
                    "filename":"/home/ania/git_tile_v2/gridding_kernels_tile.cl"
                    , "line":168
                  }
                ]
              ]
              , "details":
              [
                {
                  "type":"brief"
                  , "text":"II is an approximation."
                }
                , {
                  "type":"text"
                  , "text":"II is an approximation due to the following stallable instructions:"
                  , "links":
                  [
                    {
                      "view":"Verification statistics"
                    }
                  ]
                  , "details":
                  [
                    {
                      "type":"text"
                      , "text":"Load Operation (%L)"
                      , "links":
                      [
                        {
                          "filename":"/home/ania/git_tile_v2/gridding_kernels_tile.cl"
                          , "line":"108"
                        }
                      ]
                    }
                    , {
                      "type":"text"
                      , "text":"Load Operation (%L)"
                      , "links":
                      [
                        {
                          "filename":"/home/ania/git_tile_v2/gridding_kernels_tile.cl"
                          , "line":"109"
                        }
                      ]
                    }
                    , {
                      "type":"text"
                      , "text":"Load Operation (%L)"
                      , "links":
                      [
                        {
                          "filename":"/home/ania/git_tile_v2/gridding_kernels_tile.cl"
                          , "line":"110"
                        }
                      ]
                    }
                    , {
                      "type":"text"
                      , "text":"Load Operation (%L)"
                      , "links":
                      [
                        {
                          "filename":"/home/ania/git_tile_v2/gridding_kernels_tile.cl"
                          , "line":"113"
                        }
                      ]
                    }
                    , {
                      "type":"text"
                      , "text":"Load Operation (%L)"
                      , "links":
                      [
                        {
                          "filename":"/home/ania/git_tile_v2/gridding_kernels_tile.cl"
                          , "line":"124"
                        }
                      ]
                    }
                    , {
                      "type":"text"
                      , "text":"Load Operation (%L)"
                      , "links":
                      [
                        {
                          "filename":"/home/ania/git_tile_v2/gridding_kernels_tile.cl"
                          , "line":"132"
                        }
                      ]
                    }
                    , {
                      "type":"text"
                      , "text":"Channel Write Operation (%L)"
                      , "links":
                      [
                        {
                          "filename":"/home/ania/git_tile_v2/gridding_kernels_tile.cl"
                          , "line":"166"
                        }
                      ]
                    }
                  ]
                }
              ]
              , "children":
              [
              ]
            }
          ]
        }
      ]
    }
    , {
      "name":"Kernel: convEng"
      , "data":
      ["", "", ""]
      , "debug":
      [
        [
          {
            "filename":"/home/ania/git_tile_v2/gridding_kernels_tile.cl"
            , "line":187
          }
        ]
      ]
      , "details":
      [
        {
          "type":"brief"
          , "text":"Single work-item execution"
        }
        , {
          "type":"text"
          , "text":"Single work-item execution"
        }
        , {
          "type":"text"
          , "text":"See %L for more information"
          , "links":
          [
            {
              "guide":"Best Practices Guide : Kernels"
              , "link":"https://www.altera.com/documentation/mwh1391807516407.html#ipp1476408832230"
            }
          ]
        }
      ]
      , "children":
      [
        {
          "name":"convEng.B1"
          , "data":
          ["No", "n/a", "n/a"]
          , "debug":
          [
            [
              {
                "filename":"/home/ania/git_tile_v2/gridding_kernels_tile.cl"
                , "line":310
              }
            ]
          ]
          , "details":
          [
            {
              "type":"brief"
              , "text":"Out-of-order inner loop"
            }
            , {
              "type":"text"
              , "text":"Loop not pipelined due to:"
              , "details":
              [
                {
                  "type":"text"
                  , "text":"Loop iteration ordering: iterations of inner loop shown may get out of order with respect to the listed inner loop, as the number of iterations of the listed inner loop may be different for different iterations of this loop."
                  , "details":
                  [
                    {
                      "type":"text"
                      , "text":"convEng.B7 (%L)"
                      , "links":
                      [
                        {
                          "filename":"/home/ania/git_tile_v2/gridding_kernels_tile.cl"
                          , "line":"265"
                        }
                      ]
                    }
                    , {
                      "type":"text"
                      , "text":"convEng.B8 (%L, %L)"
                      , "links":
                      [
                        {
                          "filename":"/home/ania/git_tile_v2/gridding_kernels_tile.cl"
                          , "line":"271"
                        }
                        , {
                          "filename":"/home/ania/git_tile_v2/gridding_kernels_tile.cl"
                          , "line":"289"
                        }
                      ]
                    }
                  ]
                }
              ]
            }
            , {
              "type":"text"
              , "text":"See %L for more information."
              , "links":
              [
                {
                  "guide":"Best Practices Guide : Nested Loops"
                  , "link":"https://www.altera.com/documentation/mwh1391807516407.html#rfr1469543500580"
                }
              ]
            }
            , {
              "type":"text"
              , "text":"See %L for more information"
              , "links":
              [
                {
                  "guide":"Best Practices Guide : Nested Loops"
                  , "link":"https://www.altera.com/documentation/mwh1391807516407.html#rfr1469543500580"
                }
              ]
            }
          ]
          , "children":
          [
            {
              "name":"convEng.B2"
              , "data":
              ["Yes", ">=1", "n/a"]
              , "debug":
              [
                [
                  {
                    "filename":"/home/ania/git_tile_v2/gridding_kernels_tile.cl"
                    , "line":222
                  }
                ]
                , [
                  {
                    "filename":"/home/ania/git_tile_v2/gridding_kernels_tile.cl"
                    , "line":222
                  }
                ]
              ]
              , "details":
              [
                {
                  "type":"brief"
                  , "text":" "
                }
                , {
                  "type":"text"
                  , "text":"II is an approximation due to variable inner loop trip count."
                  , "links":
                  [
                    {
                      "view":"Verification statistics"
                    }
                  ]
                }
              ]
              , "children":
              [
                {
                  "name":"convEng.B3"
                  , "data":
                  ["Yes", "~1", "n/a"]
                  , "debug":
                  [
                    [
                      {
                        "filename":"/home/ania/git_tile_v2/gridding_kernels_tile.cl"
                        , "line":223
                      }
                    ]
                    , [
                      {
                        "filename":"/home/ania/git_tile_v2/gridding_kernels_tile.cl"
                        , "line":223
                      }
                    ]
                    , [
                      {
                        "filename":"/home/ania/git_tile_v2/gridding_kernels_tile.cl"
                        , "line":228
                      }
                    ]
                  ]
                  , "details":
                  [
                    {
                      "type":"brief"
                      , "text":"II is an approximation."
                    }
                    , {
                      "type":"text"
                      , "text":"II is an approximation due to the following stallable instruction:"
                      , "links":
                      [
                        {
                          "view":"Verification statistics"
                        }
                      ]
                      , "details":
                      [
                        {
                          "type":"text"
                          , "text":"Load Operation (%L)"
                          , "links":
                          [
                            {
                              "filename":"/home/ania/git_tile_v2/gridding_kernels_tile.cl"
                              , "line":"227"
                            }
                          ]
                        }
                      ]
                    }
                  ]
                  , "children":
                  [
                  ]
                }
              ]
            }
            , {
              "name":"convEng.B6"
              , "data":
              ["No", "n/a", "n/a"]
              , "debug":
              [
                [
                  {
                    "filename":"/home/ania/git_tile_v2/gridding_kernels_tile.cl"
                    , "line":232
                  }
                ]
                , [
                  {
                    "filename":"/home/ania/git_tile_v2/gridding_kernels_tile.cl"
                    , "line":232
                  }
                ]
              ]
              , "details":
              [
                {
                  "type":"brief"
                  , "text":"Out-of-order inner loop"
                }
                , {
                  "type":"text"
                  , "text":"Loop not pipelined due to:"
                  , "details":
                  [
                    {
                      "type":"text"
                      , "text":"Loop iteration ordering: iterations of inner loop shown may get out of order with respect to the listed inner loop, as the number of iterations of the listed inner loop may be different for different iterations of this loop."
                      , "details":
                      [
                        {
                          "type":"text"
                          , "text":"convEng.B7 (%L)"
                          , "links":
                          [
                            {
                              "filename":"/home/ania/git_tile_v2/gridding_kernels_tile.cl"
                              , "line":"265"
                            }
                          ]
                        }
                        , {
                          "type":"text"
                          , "text":"convEng.B8 (%L, %L)"
                          , "links":
                          [
                            {
                              "filename":"/home/ania/git_tile_v2/gridding_kernels_tile.cl"
                              , "line":"271"
                            }
                            , {
                              "filename":"/home/ania/git_tile_v2/gridding_kernels_tile.cl"
                              , "line":"289"
                            }
                          ]
                        }
                      ]
                    }
                  ]
                }
                , {
                  "type":"text"
                  , "text":"See %L for more information."
                  , "links":
                  [
                    {
                      "guide":"Best Practices Guide : Loops in a Single Work-Item Kernel"
                      , "link":"https://www.altera.com/documentation/mwh1391807516407.html#wfa1476380079940"
                    }
                  ]
                }
                , {
                  "type":"text"
                  , "text":"See %L for more information"
                  , "links":
                  [
                    {
                      "guide":"Best Practices Guide : Nested Loops"
                      , "link":"https://www.altera.com/documentation/mwh1391807516407.html#rfr1469543500580"
                    }
                  ]
                }
              ]
              , "children":
              [
                {
                  "name":"convEng.B7"
                  , "data":
                  ["Yes", ">=1", "n/a"]
                  , "debug":
                  [
                    [
                      {
                        "filename":"/home/ania/git_tile_v2/gridding_kernels_tile.cl"
                        , "line":265
                      }
                    ]
                    , [
                      {
                        "filename":"/home/ania/git_tile_v2/gridding_kernels_tile.cl"
                        , "line":265
                      }
                    ]
                  ]
                  , "details":
                  [
                    {
                      "type":"text"
                      , "text":"Iteration executed serially across convEng.B8. Only a single loop iteration will execute inside this region due to memory dependency:"
                      , "details":
                      [
                        {
                          "type":"text"
                          , "text":"From: Load Operation (%L)"
                          , "links":
                          [
                            {
                              "filename":"/home/ania/git_tile_v2/gridding_kernels_tile.cl"
                              , "line":"287"
                            }
                          ]
                        }
                        , {
                          "type":"text"
                          , "text":"To: Store Operation (%L)"
                          , "links":
                          [
                            {
                              "filename":"/home/ania/git_tile_v2/gridding_kernels_tile.cl"
                              , "line":"287"
                            }
                          ]
                        }
                      ]
                    }
                    , {
                      "type":"brief"
                      , "text":"Serial exe: Memory dependency"
                    }
                    , {
                      "type":"text"
                      , "text":"See %L for more information"
                      , "links":
                      [
                        {
                          "guide":"Best Practices Guide : Nested Loops"
                          , "link":"https://www.altera.com/documentation/mwh1391807516407.html#rfr1469543500580"
                        }
                      ]
                    }
                  ]
                  , "children":
                  [
                    {
                      "name":"convEng.B8"
                      , "data":
                      ["Yes", "~5", "II"]
                      , "debug":
                      [
                        [
                          {
                            "filename":"/home/ania/git_tile_v2/gridding_kernels_tile.cl"
                            , "line":271
                          }
                        ]
                        , [
                          {
                            "filename":"/home/ania/git_tile_v2/gridding_kernels_tile.cl"
                            , "line":271
                          }
                        ]
                        , [
                          {
                            "filename":"/home/ania/git_tile_v2/gridding_kernels_tile.cl"
                            , "line":289
                          }
                        ]
                      ]
                      , "details":
                      [
                        {
                          "type":"text"
                          , "text":"Compiler failed to schedule this loop with smaller II due to memory dependency:"
                          , "details":
                          [
                            {
                              "type":"text"
                              , "text":"From: Load Operation (%L)"
                              , "links":
                              [
                                {
                                  "filename":"/home/ania/git_tile_v2/gridding_kernels_tile.cl"
                                  , "line":"287"
                                }
                              ]
                            }
                            , {
                              "type":"text"
                              , "text":"To: Store Operation (%L)"
                              , "links":
                              [
                                {
                                  "filename":"/home/ania/git_tile_v2/gridding_kernels_tile.cl"
                                  , "line":"287"
                                }
                              ]
                            }
                          ]
                        }
                        , {
                          "type":"text"
                          , "text":"The critical path that prevented successful II = 4 scheduling:"
                          , "details":
                          [
                            {
                              "type":"text"
                              , "text":"4 clock cycles Hardened Floating-point Add Operation (%L)"
                              , "links":
                              [
                                {
                                  "filename":"/home/ania/git_tile_v2/gridding_kernels_tile.cl"
                                  , "line":"287"
                                }
                              ]
                            }
                            , {
                              "type":"text"
                              , "text":"1 clock cycle Load Operation (%L)"
                              , "links":
                              [
                                {
                                  "filename":"/home/ania/git_tile_v2/gridding_kernels_tile.cl"
                                  , "line":"287"
                                }
                              ]
                            }
                            , {
                              "type":"text"
                              , "text":"1 clock cycle Store Operation (%L)"
                              , "links":
                              [
                                {
                                  "filename":"/home/ania/git_tile_v2/gridding_kernels_tile.cl"
                                  , "line":"287"
                                }
                              ]
                            }
                            , {
                              "type":"text"
                              , "text":"0.28 clock cycles Or Operation (%L)"
                              , "links":
                              [
                                {
                                  "filename":"/home/ania/git_tile_v2/gridding_kernels_tile.cl"
                                  , "line":"287"
                                }
                              ]
                            }
                          ]
                        }
                        , {
                          "type":"brief"
                          , "text":"Memory dependency"
                        }
                        , {
                          "type":"text"
                          , "text":"See %L for more information"
                          , "links":
                          [
                            {
                              "guide":"Best Practices Guide : Loops in a Single Work-Item Kernel"
                              , "link":"https://www.altera.com/documentation/mwh1391807516407.html#wfa1476380079940"
                            }
                          ]
                        }
                      ]
                      , "children":
                      [
                      ]
                    }
                  ]
                }
              ]
            }
            , {
              "name":"convEng.B11"
              , "data":
              ["Yes", ">=1", "n/a"]
              , "debug":
              [
                [
                  {
                    "filename":"/home/ania/git_tile_v2/gridding_kernels_tile.cl"
                    , "line":299
                  }
                ]
                , [
                  {
                    "filename":"/home/ania/git_tile_v2/gridding_kernels_tile.cl"
                    , "line":299
                  }
                ]
              ]
              , "details":
              [
                {
                  "type":"brief"
                  , "text":" "
                }
                , {
                  "type":"text"
                  , "text":"II is an approximation due to variable inner loop trip count."
                  , "links":
                  [
                    {
                      "view":"Verification statistics"
                    }
                  ]
                }
              ]
              , "children":
              [
                {
                  "name":"convEng.B12"
                  , "data":
                  ["Yes", "~1", "n/a"]
                  , "debug":
                  [
                    [
                      {
                        "filename":"/home/ania/git_tile_v2/gridding_kernels_tile.cl"
                        , "line":300
                      }
                    ]
                    , [
                      {
                        "filename":"/home/ania/git_tile_v2/gridding_kernels_tile.cl"
                        , "line":300
                      }
                    ]
                    , [
                      {
                        "filename":"/home/ania/git_tile_v2/gridding_kernels_tile.cl"
                        , "line":304
                      }
                    ]
                  ]
                  , "details":
                  [
                    {
                      "type":"brief"
                      , "text":"II is an approximation."
                    }
                    , {
                      "type":"text"
                      , "text":"II is an approximation due to the following stallable instruction:"
                      , "links":
                      [
                        {
                          "view":"Verification statistics"
                        }
                      ]
                      , "details":
                      [
                        {
                          "type":"text"
                          , "text":"Store Operation (%L)"
                          , "links":
                          [
                            {
                              "filename":"/home/ania/git_tile_v2/gridding_kernels_tile.cl"
                              , "line":"303"
                            }
                          ]
                        }
                      ]
                    }
                  ]
                  , "children":
                  [
                  ]
                }
              ]
            }
          ]
        }
      ]
    }
  ]
}
